{"cameraMode":{"drawMode":0,"name":"Shaded","section":"Shading Mode"},"sceneLighting":true,"audioPlay":false,"sceneViewState":{"m_AlwaysRefresh":false,"showFog":true,"showSkybox":true,"showFlares":true,"showImageEffects":true,"showParticleSystems":true,"showVisualEffectGraphs":true,"m_FxEnabled":true},"in2DMode":false,"pivot":{"x":0.7141695618629456,"y":2.795311212539673,"z":-26.676729202270509},"rotation":{"x":-0.011423313058912754,"y":0.7783383131027222,"z":-0.6276258826255798,"w":-0.014234883710741997},"size":55.661624908447269,"orthographic":false}